sage_combinat_widgets/__init__.py
sage_combinat_widgets/grid_view_editor.py
sage_combinat_widgets/grid_view_widget.py
sage_combinat_widgets-0.7.8.data/data/etc/jupyter/nbconfig/notebook.d/sage-combinat-widgets.json
sage_combinat_widgets-0.7.8.data/data/share/jupyter/lab/extensions/sage-combinat-widgets-0.7.8.tgz
sage_combinat_widgets-0.7.8.data/data/share/jupyter/nbextensions/sage-combinat-widgets/extension.js
sage_combinat_widgets-0.7.8.data/data/share/jupyter/nbextensions/sage-combinat-widgets/index.js
sage_combinat_widgets-0.7.8.data/data/share/jupyter/nbextensions/sage-combinat-widgets/index.js.map
sage_widget_adapters/__init__.py
sage_widget_adapters/generic_grid_view_adapter.py
sage_widget_adapters/combinat/__init__.py
sage_widget_adapters/combinat/parallelogram_polyomino_grid_view_adapter.py
sage_widget_adapters/combinat/partition_grid_view_adapter.py
sage_widget_adapters/combinat/skew_partition_grid_view_adapter.py
sage_widget_adapters/combinat/skew_tableau_grid_view_adapter.py
sage_widget_adapters/combinat/tableau_grid_view_adapter.py
sage_widget_adapters/graphs/__init__.py
sage_widget_adapters/graphs/graph_grid_view_adapter.py
sage_widget_adapters/matrix/__init__.py
sage_widget_adapters/matrix/matrix_grid_view_adapter.py
singleton_widgets/__init__.py
singleton_widgets/singleton_widgets.py
sage_combinat_widgets-0.7.8.dist-info/LICENSE
sage_combinat_widgets-0.7.8.dist-info/METADATA
sage_combinat_widgets-0.7.8.dist-info/WHEEL
sage_combinat_widgets-0.7.8.dist-info/top_level.txt
sage_combinat_widgets-0.7.8.dist-info/RECORD
