Metadata-Version: 2.1
Name: sage-combinat-widgets
Version: 0.7.8
Summary: Jupyter widgets for SAGE Combinat
Home-page: https://github.com/sagemath/sage-combinat-widgets
Author: Odile Bénassy, Henri Derycke, Nicolas M. Thiéry
Author-email: odile.benassy@u-psud.fr
License: GPLv3+
Keywords: Jupyter,Widgets,SageMath,combinatorics
Platform: Linux
Platform: Mac OS X
Platform: Windows
Classifier: Development Status :: 3 - Alpha
Classifier: Intended Audience :: Science/Research
Classifier: Topic :: Scientific/Engineering :: Mathematics
Classifier: License :: OSI Approved :: GNU General Public License v3 or later (GPLv3+)
Classifier: Programming Language :: Python
Classifier: Programming Language :: Python :: 3
Classifier: Programming Language :: Python :: 3.5
Classifier: Programming Language :: Python :: 3.6
Classifier: Programming Language :: Python :: 3.7
Classifier: Framework :: Jupyter
Requires-Dist: ipywidgets (>=7.5.0)
Provides-Extra: docs
Requires-Dist: sage-package ; extra == 'docs'
Requires-Dist: sphinx (>=1.5) ; extra == 'docs'
